DevTools/__init__.py
DevTools/backend/__init__.py
DevTools/backend/database/__init__.py
DevTools/backend/database/antispam_db.py
DevTools/backend/database/autodelete_db.py
DevTools/backend/database/autorole_db.py
DevTools/backend/database/globalchat_db.py
DevTools/backend/database/levelsystem_db.py
DevTools/backend/database/logging_db.py
DevTools/backend/database/notes_db.py
DevTools/backend/database/profile_db.py
DevTools/backend/database/settings_db.py
DevTools/backend/database/stats_db.py
DevTools/backend/database/vc_db.py
DevTools/backend/database/warn_db.py
DevTools/backend/database/welcome_db.py
managerx_devtools-1.2026.1.11.1.dist-info/licenses/LICENSE
managerx_devtools-1.2026.1.11.1.dist-info/METADATA
managerx_devtools-1.2026.1.11.1.dist-info/WHEEL
managerx_devtools-1.2026.1.11.1.dist-info/top_level.txt
managerx_devtools-1.2026.1.11.1.dist-info/RECORD
