Metadata-Version: 2.4
Name: ManagerX-DevTools
Version: 1.2026.1.11.1
Summary: A collection of development tools for ManagerX [ManagerX Ecosystem]
Author-email: "OPPRO.NET Development" <development@oppro-network.de>
License: GPL-3.0-or-later
Project-URL: Homepage, https://oppro-network.de/
Project-URL: Repository, https://github.com/Oppro-net-Development/ManagerX-DevTools
Project-URL: Documentation, https://docs.oppro-network.de/ManagerX-DevTools/
Project-URL: Changelog, https://github.com/Oppro-net-Development/ManagerX-DevTools/releases
Project-URL: Bug Tracker, https://github.com/Oppro-net-Development/ManagerX-DevTools/issues
Keywords: ManagerX,Development,Tools,Ecosystem
Classifier: Development Status :: 4 - Beta
Classifier: Intended Audience :: Developers
Classifier: License :: OSI Approved :: GNU General Public License v3 or later (GPLv3+)
Classifier: Programming Language :: Python :: 3.8
Classifier: Programming Language :: Python :: 3.9
Classifier: Programming Language :: Python :: 3.10
Classifier: Programming Language :: Python :: 3.11
Classifier: Programming Language :: Python :: 3.12
Classifier: Operating System :: OS Independent
License-File: LICENSE
Requires-Dist: aiosqlite==0.22.1
Requires-Dist: datetime==5.1
Requires-Dist: httpx==0.24.1
Requires-Dist: psutil==5.9.5
Requires-Dist: PyYAML==6.0.1
Requires-Dist: rich==13.5.2
Dynamic: license-file
